{
  "version": "0.1.2",
  "description": "HashDit security snap to screen addresses before interaction.",
  "proposedName": "HashDit Security",
  "repository": {
    "type": "git",
    "url": "https://github.com/hashdit/metamask-snap.git"
  },
  "source": {
    "shasum": "WU8ejS2ZJakbzkizp/k/wpSphJ7B5WT2SiUaMWPGm/E=",
    "location": {
      "npm": {
        "filePath": "dist/bundle.js",
        "iconPath": "images/hashdit.svg",
        "packageName": "hashdit-snap-security",
        "registry": "https://registry.npmjs.org/"
      }
    }
  },
  "initialPermissions": {
    "endowment:transaction-insight": {
      "allowTransactionOrigin": true
    },
    "endowment:network-access": {},
    "endowment:ethereum-provider": {},
    "snap_manageState": {},
    "endowment:lifecycle-hooks": {},
    "snap_dialog": {},
    "endowment:page-home": {}
  },
  "manifestVersion": "0.1"
}
